cmdmenu.py
cmdmenu-0.1.1.dist-info/METADATA
cmdmenu-0.1.1.dist-info/RECORD
cmdmenu-0.1.1.dist-info/WHEEL
cmdmenu-0.1.1.dist-info/top_level.txt
