Metadata-Version: 2.1
Name: cmdmenu
Version: 0.1.1
Summary: A library for creating hierarchical command line arg menus.
Home-page: https://github.com/arkocal/pycmdmenu.git
Author: Ali Rasim Kocal
Author-email: arkocal@gmail.com
License: UNKNOWN
Platform: UNKNOWN
Classifier: Programming Language :: Python :: 3
Classifier: License :: OSI Approved :: MIT License
Classifier: Operating System :: OS Independent
